{
	"info": {
		"_postman_id": "2d85f599-4823-4d30-940d-b0c102d92d1e",
		"name": "Momentum",
		"schema": "https://schema.getpostman.com/json/collection/v2.1.0/collection.json"
	},
	"item": [
		{
			"name": "POST /kill",
			"request": {
				"method": "POST",
				"header": [],
				"body": {
					"mode": "raw",
					"raw": "",
					"options": {
						"raw": {
							"language": "json"
						}
					}
				},
				"url": {
					"raw": "localhost:8000/kill",
					"host": [
						"localhost"
					],
					"port": "8000",
					"path": [
						"kill"
					]
				}
			},
			"response": []
		},
		{
			"name": "GET /subscriptions",
			"request": {
				"method": "GET",
				"header": [],
				"url": {
					"raw": "localhost:8000/subscriptions",
					"host": [
						"localhost"
					],
					"port": "8000",
					"path": [
						"subscriptions"
					]
				}
			},
			"response": []
		},
		{
			"name": "POST /subscriptions",
			"request": {
				"method": "POST",
				"header": [],
				"body": {
					"mode": "raw",
					"raw": "{\n    \"exchange\": \"coinbase\",\n    \"pair\": \"LINK-USD\"\n}",
					"options": {
						"raw": {
							"language": "json"
						}
					}
				},
				"url": {
					"raw": "localhost:8000/subscriptions",
					"host": [
						"localhost"
					],
					"port": "8000",
					"path": [
						"subscriptions"
					]
				}
			},
			"response": []
		},
		{
			"name": "DEL /subscriptions",
			"request": {
				"method": "DELETE",
				"header": [],
				"body": {
					"mode": "raw",
					"raw": "{\n    \"exchange\": \"coinbase\",\n    \"pair\": \"LINK-USD\"\n}",
					"options": {
						"raw": {
							"language": "json"
						}
					}
				},
				"url": {
					"raw": "http://localhost:8000/subscriptions",
					"protocol": "http",
					"host": [
						"localhost"
					],
					"port": "8000",
					"path": [
						"subscriptions"
					]
				}
			},
			"response": []
		},
		{
			"name": "GET /algorithms",
			"request": {
				"method": "GET",
				"header": [],
				"url": {
					"raw": "localhost:8000/algorithms",
					"host": [
						"localhost"
					],
					"port": "8000",
					"path": [
						"algorithms"
					]
				}
			},
			"response": []
		},
		{
			"name": "POST /algorithms",
			"request": {
				"method": "POST",
				"header": [],
				"body": {
					"mode": "raw",
					"raw": "{\n        \"algorithm\": \"ema1226\",\n        \"exchange\": \"coinbase\",\n        \"pair\": \"LINK-USD\",\n        \"period\": \"1m\",\n        \"size\": \"160\",\n        \"lastTrade\": \"sell,9.60\"\n    }",
					"options": {
						"raw": {
							"language": "json"
						}
					}
				},
				"url": {
					"raw": "localhost:8000/algorithms",
					"host": [
						"localhost"
					],
					"port": "8000",
					"path": [
						"algorithms"
					]
				}
			},
			"response": []
		},
		{
			"name": "DEL /algorithms",
			"request": {
				"method": "DELETE",
				"header": [],
				"body": {
					"mode": "raw",
					"raw": "{\n    \"algorithm\": \"ema1226\",\n    \"exchange\": \"coinbase\",\n    \"pair\": \"LINK-USD\"\n}",
					"options": {
						"raw": {
							"language": "json"
						}
					}
				},
				"url": {
					"raw": "localhost:8000/algorithms",
					"host": [
						"localhost"
					],
					"port": "8000",
					"path": [
						"algorithms"
					]
				}
			},
			"response": []
		},
		{
			"name": "GET /last-trades",
			"request": {
				"method": "GET",
				"header": [],
				"url": {
					"raw": "localhost:8000/trades",
					"host": [
						"localhost"
					],
					"port": "8000",
					"path": [
						"trades"
					]
				}
			},
			"response": []
		}
	],
	"event": [
		{
			"listen": "prerequest",
			"script": {
				"id": "fd61843d-37f9-4893-acbf-24f2566374e0",
				"type": "text/javascript",
				"exec": [
					""
				]
			}
		},
		{
			"listen": "test",
			"script": {
				"id": "182001bc-1fed-4b3e-a929-9f41ea6e21b6",
				"type": "text/javascript",
				"exec": [
					""
				]
			}
		}
	],
	"protocolProfileBehavior": {}
}